iw041/__init__.py
iw041-0.1.0.dist-info/WHEEL
iw041-0.1.0.dist-info/METADATA
iw041-0.1.0.dist-info/RECORD
