Metadata-Version: 2.1
Name: iw041
Version: 0.1.0
Summary: This is a test project from iw041.
Author: Ingolf Wassmann
Author-email: ingolf.wassmann@gmail.com
Requires-Python: >=3.7,<4.0
Classifier: Programming Language :: Python :: 3
Classifier: Programming Language :: Python :: 3.7
Classifier: Programming Language :: Python :: 3.8
Requires-Dist: pandas (==1.0.1)
